bbb_client/__init__.py
bbb_client/domain/__init__.py
bbb_client/domain/meeting_management/__init__.py
bbb_client/domain/meeting_management/model.py
bbb_client/entry_points.py
bbb_client/infrastructure/__init__.py
bbb_client/infrastructure/click/__init__.py
bbb_client/infrastructure/click/bbb.py
bbb_client/interfaces/__init__.py
bbb_client/interfaces/from_terminal.py
bbb_client/interfaces/to_terminal.py
bbb_client/py.typed
bbb_client/use_cases/__init__.py
bbb_client/use_cases/search_meetings.py
bbb_client-0.2.0.dist-info/COPYING
bbb_client-0.2.0.dist-info/METADATA
bbb_client-0.2.0.dist-info/WHEEL
bbb_client-0.2.0.dist-info/entry_points.txt
bbb_client-0.2.0.dist-info/RECORD
