Metadata-Version: 2.1
Name: bbb-client
Version: 0.2.0
Summary: Client library and CLI to interact with the BBB API
License: GPL-3.0-or-later
Author: Tanguy Le Carrour
Author-email: tlecarrour@easter-eggs.com
Requires-Python: >=3.9,<4.0
Classifier: License :: OSI Approved :: GNU General Public License v3 or later (GPLv3+)
Classifier: Programming Language :: Python :: 3
Classifier: Programming Language :: Python :: 3.9
Classifier: Programming Language :: Python :: 3.10
Classifier: Programming Language :: Python :: 3.11
Classifier: Programming Language :: Python :: 3.12
Requires-Dist: click (>=8.1.7,<9.0.0)
Requires-Dist: requests (>=2.31.0,<3.0.0)
Requires-Dist: untangle (>=1.2.1,<2.0.0)
